remu_operator/__init__.py
remu_operator-1.0.1.dist-info/LICENSE
remu_operator-1.0.1.dist-info/METADATA
remu_operator-1.0.1.dist-info/WHEEL
remu_operator-1.0.1.dist-info/entry_points.txt
remu_operator-1.0.1.dist-info/top_level.txt
remu_operator-1.0.1.dist-info/RECORD
